turban/VERSION
turban/__init__.py
turban/turban.py
turban_toolbox-0.0.1.dist-info/LICENSE
turban_toolbox-0.0.1.dist-info/METADATA
turban_toolbox-0.0.1.dist-info/WHEEL
turban_toolbox-0.0.1.dist-info/top_level.txt
turban_toolbox-0.0.1.dist-info/RECORD
